{
  "db_name": "PostgreSQL",
  "query": "SELECT * from users WHERE id = $1 LIMIT 1",
  "describe": {
    "columns": [
      {
        "ordinal": 0,
        "name": "id",
        "type_info": "Text"
      },
      {
        "ordinal": 1,
        "name": "email",
        "type_info": "Text"
      },
      {
        "ordinal": 2,
        "name": "slack_id",
        "type_info": "Text"
      },
      {
        "ordinal": 3,
        "name": "first_name",
        "type_info": "Text"
      },
      {
        "ordinal": 4,
        "name": "last_name",
        "type_info": "Text"
      },
      {
        "ordinal": 5,
        "name": "verification_status",
        "type_info": "Text"
      },
      {
        "ordinal": 6,
        "name": "ysws_eligible",
        "type_info": "Bool"
      },
      {
        "ordinal": 7,
        "name": "created_at",
        "type_info": "Timestamptz"
      },
      {
        "ordinal": 8,
        "name": "updated_at",
        "type_info": "Timestamptz"
      },
      {
        "ordinal": 9,
        "name": "hca_access_token",
        "type_info": "Text"
      },
      {
        "ordinal": 10,
        "name": "hca_refresh_token",
        "type_info": "Text"
      },
      {
        "ordinal": 11,
        "name": "hca_token_expires_at",
        "type_info": "Timestamptz"
      }
    ],
    "parameters": {
      "Left": [
        "Text"
      ]
    },
    "nullable": [
      false,
      false,
      false,
      false,
      false,
      false,
      false,
      false,
      false,
      false,
      false,
      false
    ]
  },
  "hash": "d8da144de3035b0974cb2a7f1f79db37e71725c0879f334735c72ce7fcf3554b"
}
